gemini_tool_agent/agent.py
gemini_tool_agent-0.1.5.dist-info/METADATA
gemini_tool_agent-0.1.5.dist-info/WHEEL
gemini_tool_agent-0.1.5.dist-info/top_level.txt
gemini_tool_agent-0.1.5.dist-info/RECORD
