Metadata-Version: 2.4
Name: gemini-tool-agent
Version: 0.1.5
Summary: A tool-aware agent powered by Gemini for structured query handling
Author-email: Paul Fruitful <fruitful2007@outlook.com>
License: MIT
Requires-Python: >=3.8
Requires-Dist: google-genai>=0.3.2
